VLSI/USR-Dflipflop/dflipflop.v
module dflipflop(q, d, clk, reset);
input d, clk, reset;
output reg q;

always@(posedge clk)
begin
	if(reset == 1'b1)
		q<=1'b0;
	else
		q<=d;
end
endmodule

VLSI/USR-Dflipflop/dflipflop_tb.v
`include "dflipflop.v"

module dflipflop_tb;

reg d, clk, reset;

wire q;
	
dflipflop  d1 (q, d, clk, reset);
		
always 
begin
	clk = 1'b0;
	#5;
	clk = 1'b1;
	#5;
end
	
initial	begin
$dumpfile("dflipflop_tb.vcd"); 
$dumpvars;
 		
reset = 1;

#10
reset = 0; 
d = 1;

#10
d = 0;

#10 
d = 1;

#10 $finish;
end
		
initial
	$monitor ($time, "   q = %b, d = %b, clk = %b, reset = %b",q,d,clk,reset);
	
endmodule

VLSI/USR-Dflipflop/dflipflop_tb.vcd
$date
	Sat Sep 12 15:11:34 2020
$end
$version
	Icarus Verilog
$end
$timescale
	1s
$end
$scope module dflipflop_tb $end
$var wire 1 ! q $end
$var reg 1 " clk $end
$var reg 1 # d $end
$var reg 1 $ reset $end
$scope module d1 $end
$var wire 1 " clk $end
$var wire 1 # d $end
$var wire 1 $ reset $end
$var reg 1 ! q $end
$upscope $end
$upscope $end
$enddefinitions $end
#0
$dumpvars
1$
x#
0"
x!
$end
#5
0!
1"
#10
0"
1#
0$
#15
1!
1"
#20
0"
0#
#25
0!
1"
#30
0"
1#
#35
1!
1"
